<?xml version="1.0" encoding="UTF-8" standalone="yes"?>
<unit xmlns="http://www.sdml.info/srcML/src" xmlns:cpp="http://www.sdml.info/srcML/cpp" xmlns:lit="http://www.sdml.info/srcML/literal" xmlns:op="http://www.sdml.info/srcML/operator" xmlns:type="http://www.sdml.info/srcML/modifier" xmlns:pos="http://www.sdml.info/srcML/position" language="C#" filename="D:\Research\Subjects\Glimpse-master\source\Glimpse.Core\Framework\IDiscoverableCollection.cs" pos:tabs="8"><using pos:line="1" pos:column="1">using <name pos:line="1" pos:column="7">System</name>;</using>
<using pos:line="2" pos:column="1">using <name><name pos:line="2" pos:column="7">System</name><op:operator pos:line="2" pos:column="13">.</op:operator><name pos:line="2" pos:column="14">Collections</name><op:operator pos:line="2" pos:column="25">.</op:operator><name pos:line="2" pos:column="26">Generic</name></name>;</using>

<namespace pos:line="4" pos:column="1">namespace <name><name pos:line="4" pos:column="11">Glimpse</name><op:operator pos:line="4" pos:column="18">.</op:operator><name pos:line="4" pos:column="19">Core</name><op:operator pos:line="4" pos:column="23">.</op:operator><name pos:line="4" pos:column="24">Framework</name></name>
<block pos:line="5" pos:column="1">{
    <comment type="line" pos:line="6" pos:column="5">/// &lt;summary&gt;</comment>
    <comment type="line" pos:line="7" pos:column="5">/// Defines methods to self discover collection content.</comment>
    <comment type="line" pos:line="8" pos:column="5">/// &lt;/summary&gt;</comment>
    <comment type="line" pos:line="9" pos:column="5">/// &lt;typeparam name="T"&gt;Collection item type&lt;/typeparam&gt;</comment>
    <class type="interface"><specifier pos:line="10" pos:column="5">public</specifier> interface <name><name pos:line="10" pos:column="22">IDiscoverableCollection</name><argument_list pos:line="10" pos:column="45">&lt;<argument><name pos:line="10" pos:column="46">T</name></argument>&gt;</argument_list></name> <super pos:line="10" pos:column="49">: <name><name pos:line="10" pos:column="51">ICollection</name><argument_list pos:line="10" pos:column="62">&lt;<argument><name pos:line="10" pos:column="63">T</name></argument>&gt;</argument_list></name></super>
    <block pos:line="11" pos:column="5">{
        <comment type="line" pos:line="12" pos:column="9">/// &lt;summary&gt;</comment>
        <comment type="line" pos:line="13" pos:column="9">/// Gets a value indicating whether [auto discover].</comment>
        <comment type="line" pos:line="14" pos:column="9">/// &lt;/summary&gt;</comment>
        <comment type="line" pos:line="15" pos:column="9">/// &lt;value&gt;&lt;c&gt;true&lt;/c&gt; if [auto discover]; otherwise, &lt;c&gt;false&lt;/c&gt;.&lt;/value&gt;</comment>
        <comment type="line" pos:line="16" pos:column="9">/// &lt;remarks&gt;</comment>
        <comment type="line" pos:line="17" pos:column="9">/// Indicates whether the system can automatically call Discover()</comment>
        <comment type="line" pos:line="18" pos:column="9">/// &lt;/remarks&gt;</comment>
        <decl_stmt><decl><type><name pos:line="19" pos:column="9">bool</name></type> <name pos:line="19" pos:column="14">AutoDiscover</name> <block pos:line="19" pos:column="27">{ <function_decl><name pos:line="19" pos:column="29">get</name>;</function_decl> }</block></decl></decl_stmt>

        <comment type="line" pos:line="21" pos:column="9">/// &lt;summary&gt;</comment>
        <comment type="line" pos:line="22" pos:column="9">/// Gets the discovery location.</comment>
        <comment type="line" pos:line="23" pos:column="9">/// &lt;/summary&gt;</comment>
        <comment type="line" pos:line="24" pos:column="9">/// &lt;value&gt;The discovery location.&lt;/value&gt;</comment>
        <decl_stmt><decl><type><name pos:line="25" pos:column="9">string</name></type> <name pos:line="25" pos:column="16">DiscoveryLocation</name> <block pos:line="25" pos:column="34">{ <function_decl><name pos:line="25" pos:column="36">get</name>;</function_decl> }</block></decl></decl_stmt>

        <comment type="line" pos:line="27" pos:column="9">/// &lt;summary&gt;</comment>
        <comment type="line" pos:line="28" pos:column="9">/// Ignores the type.</comment>
        <comment type="line" pos:line="29" pos:column="9">/// &lt;/summary&gt;</comment>
        <comment type="line" pos:line="30" pos:column="9">/// &lt;param name="type"&gt;The type.&lt;/param&gt;</comment>
        <function_decl><type><name pos:line="31" pos:column="9">void</name></type> <name pos:line="31" pos:column="14">IgnoreType</name><parameter_list pos:line="31" pos:column="24">(<param><decl><type><name pos:line="31" pos:column="25">Type</name></type> <name pos:line="31" pos:column="30">type</name></decl></param>)</parameter_list>;</function_decl>

        <comment type="line" pos:line="33" pos:column="9">/// &lt;summary&gt;</comment>
        <comment type="line" pos:line="34" pos:column="9">/// Discovers this instance. Triggers the loading of content.</comment>
        <comment type="line" pos:line="35" pos:column="9">/// &lt;/summary&gt;</comment>
        <function_decl><type><name pos:line="36" pos:column="9">void</name></type> <name pos:line="36" pos:column="14">Discover</name><parameter_list pos:line="36" pos:column="22">()</parameter_list>;</function_decl>
    }</block></class>
}</block></namespace></unit>
